find_missing/__init__.py
find_missing/__main__.py
find_missing/find_missing.py
find_missing-1.1.10.dist-info/entry_points.txt
find_missing-1.1.10.dist-info/WHEEL
find_missing-1.1.10.dist-info/METADATA
find_missing-1.1.10.dist-info/RECORD
