Metadata-Version: 2.1
Name: find-missing
Version: 1.1.10
Summary: 
Home-page: https://github.com/licht1stein/find-missing
License: MIT
Author: MB
Author-email: mb@m1k.pw
Requires-Python: >=3.7,<4.0
Classifier: License :: OSI Approved :: MIT License
Classifier: Programming Language :: Python :: 3
Classifier: Programming Language :: Python :: 3.7
Requires-Dist: click (>=7.0,<8.0)
